README.md
setup.cfg
setup.py
jerry_distributions/Binomialdistribution.py
jerry_distributions/Gaussiandistribution.py
jerry_distributions/Generaldistribution.py
jerry_distributions/__init__.py
jerry_distributions.egg-info/PKG-INFO
jerry_distributions.egg-info/SOURCES.txt
jerry_distributions.egg-info/dependency_links.txt
jerry_distributions.egg-info/not-zip-safe
jerry_distributions.egg-info/top_level.txt